mongodm/__init__.py
mongodm/errors.py
mongodm/types.py
python_mongodm-0.1.6.dist-info/LICENSE
python_mongodm-0.1.6.dist-info/METADATA
python_mongodm-0.1.6.dist-info/WHEEL
python_mongodm-0.1.6.dist-info/top_level.txt
python_mongodm-0.1.6.dist-info/RECORD
